audio_connected/__init__.py
audio_connected-0.202512302127.dist-info/METADATA
audio_connected-0.202512302127.dist-info/WHEEL
audio_connected-0.202512302127.dist-info/entry_points.txt
audio_connected-0.202512302127.dist-info/licenses/LICENSE
audio_connected-0.202512302127.dist-info/RECORD
