Metadata-Version: 2.4
Name: audio-connected
Version: 0.202512302127
Summary: Watches PulseAudio events for new sinks connected, and if the name matches the configured name, make that sink the default sink.
Project-URL: Issues, https://github.com/mortenlj/audio-connected/issues
Project-URL: Repository, https://github.com/mortenlj/audio-connected
Author-email: Morten Lied Johansen <mortenjo@ifi.uio.no>
License-Expression: MIT
License-File: LICENSE
Requires-Python: <4.0,>=3.11
Requires-Dist: pulsectl<25.0.0,>=24.0.0
